{"d": {"count": 12907, "next": "https://hub.docker.com/v2/search/repositories/?page=2&page_size=3&query=grafana", "previous": "", "results": [{"repo_name": "grafana/grafana", "short_description": "The official Grafana docker container", "star_count": 3506, "pull_count": 5156292407, "repo_owner": "", "is_automated": false, "is_official": false}, {"repo_name": "grafana/loki", "short_description": "Loki - Cloud Native Log Aggregation by Grafana", "star_count": 322, "pull_count": 4557093900, "repo_owner": "", "is_automated": false, "is_official": false}, {"repo_name": "grafana/grafana-image-renderer", "short_description": "", "star_count": 32, "pull_count": 868921672, "repo_owner": "", "is_automated": false, "is_official": false}]}}