{"d": {"count": 50, "next": "https://hub.docker.com/v2/search/repositories/?page=2&page_size=3&query=cheerio", "previous": "", "results": [{"repo_name": "vivekmjude/cheerio", "short_description": "Golang VueJS", "star_count": 0, "pull_count": 184, "repo_owner": "", "is_automated": false, "is_official": false}, {"repo_name": "martinjohn/cheerio", "short_description": "", "star_count": 0, "pull_count": 51, "repo_owner": "", "is_automated": false, "is_official": false}, {"repo_name": "snickch/cheerio-api", "short_description": "Cheerio with REST-API - documentation: https://github.com/SnickCH/cheerio-api", "star_count": 0, "pull_count": 169, "repo_owner": "", "is_automated": false, "is_official": false}]}}