{"d": {"items": [{"tags": ["javascript", "uglifyjs", "sentry", "source-maps", "raven"], "owner": {"account_id": 3843914, "reputation": 2129, "user_id": 3186123, "user_type": "registered", "accept_rate": 67, "profile_image": "https://www.gravatar.com/avatar/00a8a4f5098181e27908a69c9ea115fb?s=256&d=identicon&r=PG&f=y&so-version=2", "display_name": "Ofer Velich", "link": "https://stackoverflow.com/users/3186123/ofer-velich"}, "is_answered": true, "view_count": 39717, "closed_date": 1477126296, "answer_count": 2, "score": 85, "last_activity_date": 1546413622, "creation_date": 1417973366, "last_edit_date": 1546413622, "question_id": 27345520, "link": "https://stackoverflow.com/questions/27345520/source-maps-files-in-production-is-it-safe", "closed_reason": "Opinion-based", "title": "Source maps files in production - Is it safe?"}, {"tags": ["javascript", "ios", "sentry"], "owner": {"account_id": 24388393, "reputation": 801, "user_id": 18318767, "user_type": "registered", "profile_image": "https://lh3.googleusercontent.com/a/AATXAJyvrXQu9dc3DOY-foGCmvPp8YmZDNB7u7xWpSn_=k-s256", "display_name": "Thomas Stewart", "link": "https://stackoverflow.com/users/18318767/thomas-stewart"}, "is_answered": true, "view_count": 55375, "answer_count": 6, "score": 70, "last_activity_date": 1750100055, "creation_date": 1645908489, "question_id": 71280168, "content_license": "CC BY-SA 4.0", "link": "https://stackoverflow.com/questions/71280168/javascript-typeerror-load-failed-error-when-calling-fetch-on-ios", "title": "Javascript &quot;TypeError: Load Failed&quot; error when calling &quot;fetch&quot; on iOS"}, {"tags": ["javascript", "error-handling", "sentry"], "owner": {"account_id": 1714001, "reputation": 7885, "user_id": 1571491, "user_type": "registered", "accept_rate": 73, "profile_image": "https://i.sstatic.net/j1oTV.png?s=256", "display_name": "Jurosh", "link": "https://stackoverflow.com/users/1571491/jurosh"}, "is_answered": true, "view_count": 47621, "accepted_answer_id": 56736902, "answer_count": 6, "score": 67, "last_activity_date": 1770222897, "creation_date": 1527805136, "question_id": 50633580, "content_license": "CC BY-SA 4.0", "link": "https://stackoverflow.com/questions/50633580/how-to-report-console-error-with-sentry", "title": "How to report console.error with Sentry?"}, {"tags": ["javascript", "ios", "sentry"], "owner": {"account_id": 295003, "reputation": 26615, "user_id": 599184, "user_type": "registered", "accept_rate": 78, "profile_image": "https://i.sstatic.net/tjsXC.jpg?s=256", "display_name": "Leo Jiang", "link": "https://stackoverflow.com/users/599184/leo-jiang"}, "is_answered": true, "view_count": 18065, "answer_count": 5, "score": 62, "last_activity_date": 1651588862, "creation_date": 1555555393, "last_edit_date": 1561052930, "question_id": 55738408, "content_license": "CC BY-SA 4.0", "link": "https://stackoverflow.com/questions/55738408/javascript-typeerror-cancelled-error-when-calling-fetch-on-ios", "title": "Javascript &quot;TypeError: cancelled&quot; error when calling &quot;fetch&quot; on iOS"}, {"tags": ["javascript", "logging", "sentry"], "owner": {"account_id": 343968, "reputation": 11038, "user_id": 676001, "user_type": "registered", "accept_rate": 77, "profile_image": "https://www.gravatar.com/avatar/0c88ccfd338195785bd30bac30041b59?s=256&d=identicon&r=PG", "display_name": "bertday", "link": "https://stackoverflow.com/users/676001/bertday"}, "is_answered": true, "view_count": 55251, "accepted_answer_id": 67884468, "answer_count": 5, "score": 48, "last_activity_date": 1722283238, "creation_date": 1510847312, "last_edit_date": 1609952244, "question_id": 47333846, "content_license": "CC BY-SA 4.0", "link": "https://stackoverflow.com/questions/47333846/how-do-i-test-that-sentry-is-reporting-errors", "title": "How do I test that Sentry is reporting errors?"}, {"tags": ["c#", "serilog", ".net-6.0", "sentry", "ilogger"], "owner": {"account_id": 2097110, "reputation": 10440, "user_id": 1865613, "user_type": "registered", "accept_rate": 64, "profile_image": "https://i.sstatic.net/AJKXMEm8.png?s=256", "display_name": "\u02c8v\u0254l\u0259", "link": "https://stackoverflow.com/users/1865613/%cb%88v%c9%94l%c9%99"}, "is_answered": true, "view_count": 91576, "accepted_answer_id": 71599384, "answer_count": 5, "score": 38, "last_activity_date": 1699741002, "creation_date": 1648110976, "question_id": 71599246, "content_license": "CC BY-SA 4.0", "link": "https://stackoverflow.com/questions/71599246/how-to-configure-and-use-serilog-in-asp-net-core-6", "title": "How to configure and use Serilog in ASP.NET Core 6?"}, {"tags": ["javascript", "reactjs", "sentry"], "owner": {"account_id": 7315486, "reputation": 10675, "user_id": 5573294, "user_type": "registered", "accept_rate": 68, "profile_image": "https://i.sstatic.net/f7wtO.jpg?s=256", "display_name": "Canovice", "link": "https://stackoverflow.com/users/5573294/canovice"}, "is_answered": true, "view_count": 26364, "answer_count": 8, "score": 37, "last_activity_date": 1712153777, "creation_date": 1604523650, "question_id": 64687662, "content_license": "CC BY-SA 4.0", "link": "https://stackoverflow.com/questions/64687662/react-sentry-for-error-reporting-how-to-not-send-errors-from-dev-localhost", "title": "React / Sentry for Error Reporting - How to not send errors from dev / localhost"}, {"tags": ["django", "sentry", "data-cleaning"], "owner": {"account_id": 144122, "reputation": 1261, "user_id": 352944, "user_type": "registered", "accept_rate": 57, "profile_image": "https://i.sstatic.net/8ekCs.jpg?s=256", "display_name": "equalium", "link": "https://stackoverflow.com/users/352944/equalium"}, "is_answered": true, "view_count": 13444, "answer_count": 4, "score": 32, "last_activity_date": 1526997313, "creation_date": 1338372200, "last_edit_date": 1402581191, "question_id": 10814097, "content_license": "CC BY-SA 3.0", "link": "https://stackoverflow.com/questions/10814097/how-to-clear-maintain-a-django-sentry-database", "title": "How to clear / maintain a django-sentry database?"}, {"tags": ["javascript", "ios", "microsoft-edge", "sentry"], "owner": {"account_id": 16416002, "reputation": 884, "user_id": 11858171, "user_type": "registered", "profile_image": "https://i.sstatic.net/dfFaG.jpg?s=256", "display_name": "zerdox", "link": "https://stackoverflow.com/users/11858171/zerdox"}, "is_answered": true, "view_count": 5888, "accepted_answer_id": 69576781, "answer_count": 1, "score": 30, "last_activity_date": 1634242362, "creation_date": 1632177117, "last_edit_date": 1632235083, "question_id": 69261499, "content_license": "CC BY-SA 4.0", "link": "https://stackoverflow.com/questions/69261499/what-is-instantsearchsdkjsbridgeclearhighlight", "title": "What is instantSearchSDKJSBridgeClearHighlight?"}, {"tags": ["python", "django", "sentry", "raven"], "owner": {"account_id": 2212282, "reputation": 6081, "user_id": 1953785, "user_type": "registered", "accept_rate": 67, "profile_image": "https://www.gravatar.com/avatar/6d65fc8887ead353a7d766e08e2cbbdd?s=256&d=identicon&r=PG", "display_name": "Agam Rafaeli-Farhadian", "link": "https://stackoverflow.com/users/1953785/agam-rafaeli-farhadian"}, "is_answered": true, "view_count": 19280, "accepted_answer_id": 36261343, "answer_count": 2, "score": 27, "last_activity_date": 1459164165, "creation_date": 1457518875, "last_edit_date": 1458462965, "question_id": 35888806, "content_license": "CC BY-SA 3.0", "link": "https://stackoverflow.com/questions/35888806/how-do-you-configure-a-sentry-raven-client-in-a-development-environment-to-not-s", "title": "How do you configure a Sentry raven client in a development environment to not send exceptions and still work?"}, {"tags": ["django", "sentry"], "owner": {"account_id": 19476, "reputation": 11740, "user_id": 45698, "user_type": "registered", "accept_rate": 79, "profile_image": "https://www.gravatar.com/avatar/a802210cc39f5ea67135181a8d61aa11?s=256&d=identicon&r=PG", "display_name": "Hugo Rodger-Brown", "link": "https://stackoverflow.com/users/45698/hugo-rodger-brown"}, "is_answered": true, "view_count": 9490, "accepted_answer_id": 13332577, "answer_count": 2, "score": 26, "last_activity_date": 1382543425, "creation_date": 1352643750, "last_edit_date": 1352647294, "question_id": 13331973, "content_license": "CC BY-SA 3.0", "link": "https://stackoverflow.com/questions/13331973/how-does-sentry-aggregate-errors", "title": "How does Sentry aggregate errors?"}, {"tags": ["python", "django", "sentry"], "owner": {"account_id": 7733276, "reputation": 473, "user_id": 5855645, "user_type": "registered", "profile_image": "https://i.sstatic.net/E9hy3.jpg?s=256", "display_name": "Dongeon Kim", "link": "https://stackoverflow.com/users/5855645/dongeon-kim"}, "is_answered": true, "view_count": 8599, "accepted_answer_id": 52937429, "answer_count": 2, "score": 26, "last_activity_date": 1627819345, "creation_date": 1540204715, "last_edit_date": 1540283271, "question_id": 52927353, "content_license": "CC BY-SA 4.0", "link": "https://stackoverflow.com/questions/52927353/how-to-ignore-a-logger-in-the-sentry-python-sdk", "title": "How to ignore a logger in the Sentry Python SDK"}, {"tags": ["javascript", "angularjs", "twitter-bootstrap", "runtime-error", "sentry"], "owner": {"account_id": 2672014, "reputation": 378, "user_id": 2309205, "user_type": "registered", "accept_rate": 0, "profile_image": "https://www.gravatar.com/avatar/d78e9f12f353e842ded341d2c306f8bf?s=256&d=identicon&r=PG", "display_name": "mryarbles", "link": "https://stackoverflow.com/users/2309205/mryarbles"}, "is_answered": true, "view_count": 1431, "answer_count": 2, "score": 25, "last_activity_date": 1510256962, "creation_date": 1466445490, "last_edit_date": 1592644375, "question_id": 37928917, "content_license": "CC BY-SA 4.0", "link": "https://stackoverflow.com/questions/37928917/added-sentry-debugging-getting-long-string-as-undefined", "title": "Added Sentry debugging, getting long string as undefined"}, {"tags": ["python", "django", "postgresql", "sentry", "heroku-postgres"], "owner": {"account_id": 198108, "reputation": 428, "user_id": 442576, "user_type": "registered", "accept_rate": 75, "profile_image": "https://www.gravatar.com/avatar/bdbeb5a17fd7f514e215a97f4b2676c6?s=256&d=identicon&r=PG", "display_name": "dhargan", "link": "https://stackoverflow.com/users/442576/dhargan"}, "is_answered": true, "view_count": 23350, "answer_count": 6, "score": 25, "last_activity_date": 1760653539, "creation_date": 1535418832, "question_id": 52048778, "content_license": "CC BY-SA 4.0", "link": "https://stackoverflow.com/questions/52048778/operationalerror-cursor-django-curs-id-does-not-exist", "title": "OperationalError: cursor &quot;_django_curs_&lt;id&gt;&quot; does not exist"}, {"tags": ["angular", "continuous-integration", "source-maps", "sentry"], "owner": {"account_id": 5563118, "reputation": 997, "user_id": 4518577, "user_type": "registered", "accept_rate": 100, "profile_image": "https://i.sstatic.net/O9bge.png?s=256", "display_name": "Nikola Jankovic", "link": "https://stackoverflow.com/users/4518577/nikola-jankovic"}, "is_answered": true, "view_count": 4069, "accepted_answer_id": 72322432, "answer_count": 4, "score": 24, "last_activity_date": 1675096026, "creation_date": 1537842628, "question_id": 52489770, "content_license": "CC BY-SA 4.0", "link": "https://stackoverflow.com/questions/52489770/how-to-generate-sourcemaps-using-angular-cli-and-upload-them-to-sentry", "title": "How to generate sourcemaps using Angular CLI and upload them to Sentry?"}], "has_more": true, "quota_max": 300, "quota_remaining": 223}}