{"d": {"count": 16930, "next": "https://hub.docker.com/v2/search/repositories/?page=2&page_size=3&query=mongodb", "previous": "", "results": [{"repo_name": "mongodb/mongodb-community-server", "short_description": "The Official MongoDB Community Server", "star_count": 178, "pull_count": 20549222, "repo_owner": "", "is_automated": false, "is_official": false}, {"repo_name": "mongodb/mongodb-enterprise-server", "short_description": "The Official MongoDB Enterprise Advanced Server.", "star_count": 15, "pull_count": 5209605, "repo_owner": "", "is_automated": false, "is_official": false}, {"repo_name": "mongodb/mongodb-atlas-local", "short_description": "Create, manage, and automate MongoDB Atlas Local resources from docker", "star_count": 10, "pull_count": 4705544, "repo_owner": "", "is_automated": false, "is_official": false}]}}