{"d": [{"url": "https://api.github.com/repos/storybookjs/storybook/releases/290847879", "assets_url": "https://api.github.com/repos/storybookjs/storybook/releases/290847879/assets", "upload_url": "https://uploads.github.com/repos/storybookjs/storybook/releases/290847879/assets{?name,label}", "html_url": "https://github.com/storybookjs/storybook/releases/tag/v10.3.0-alpha.12", "id": 290847879, "author": {"login": "github-actions[bot]", "id": 41898282, "node_id": "MDM6Qm90NDE4OTgyODI=", "avatar_url": "https://avatars.githubusercontent.com/in/15368?v=4", "gravatar_id": "", "url": "https://api.github.com/users/github-actions%5Bbot%5D", "html_url": "https://github.com/apps/github-actions", "followers_url": "https://api.github.com/users/github-actions%5Bbot%5D/followers", "following_url": "https://api.github.com/users/github-actions%5Bbot%5D/following{/other_user}", "gists_url": "https://api.github.com/users/github-actions%5Bbot%5D/gists{/gist_id}", "starred_url": "https://api.github.com/users/github-actions%5Bbot%5D/starred{/owner}{/repo}", "subscriptions_url": "https://api.github.com/users/github-actions%5Bbot%5D/subscriptions", "organizations_url": "https://api.github.com/users/github-actions%5Bbot%5D/orgs", "repos_url": "https://api.github.com/users/github-actions%5Bbot%5D/repos", "events_url": "https://api.github.com/users/github-actions%5Bbot%5D/events{/privacy}", "received_events_url": "https://api.github.com/users/github-actions%5Bbot%5D/received_events", "type": "Bot", "user_view_type": "public", "site_admin": false}, "node_id": "RE_kwDOAzqfmc4RVfyH", "tag_name": "v10.3.0-alpha.12", "target_commitish": "next-release", "name": "v10.3.0-alpha.12", "draft": false, "immutable": false, "prerelease": true, "created_at": "2026-02-26T10:55:57Z", "updated_at": "2026-02-26T11:04:46Z", "published_at": "2026-02-26T11:04:46Z", "assets": [], "tarball_url": "https://api.github.com/repos/storybookjs/storybook/tarball/v10.3.0-alpha.12", "zipball_url": "https://api.github.com/repos/storybookjs/storybook/zipball/v10.3.0-alpha.12", "body": "## 10.3.0-alpha.12\n\n- Builder-Vite: Prevent config duplication - [#33883](https://github.com/storybookjs/storybook/pull/33883), thanks @copilot-swe-agent!\n- CLI: Fix React native web A11y issues - [#33937](https://github.com/storybookjs/storybook/pull/33937), thanks @jonniebigodes!\n- Core: Ensure telemetry is never triggered on initial load of checklist data - [#33918](https://github.com/storybookjs/storybook/pull/33918), thanks @ghengeveld!\n- Eslint: Fix ESLint 10 compatibility in eslint-plugin-storybook rules - [#33884](https://github.com/storybookjs/storybook/pull/33884), thanks @copilot-swe-agent!\n- Test: Update @testing-library/jest-dom - [#33928](https://github.com/storybookjs/storybook/pull/33928), thanks @valentinpalkovic!\n", "mentions_count": 4}, {"url": "https://api.github.com/repos/storybookjs/storybook/releases/290835842", "assets_url": "https://api.github.com/repos/storybookjs/storybook/releases/290835842/assets", "upload_url": "https://uploads.github.com/repos/storybookjs/storybook/releases/290835842/assets{?name,label}", "html_url": "https://github.com/storybookjs/storybook/releases/tag/v10.2.13", "id": 290835842, "author": {"login": "github-actions[bot]", "id": 41898282, "node_id": "MDM6Qm90NDE4OTgyODI=", "avatar_url": "https://avatars.githubusercontent.com/in/15368?v=4", "gravatar_id": "", "url": "https://api.github.com/users/github-actions%5Bbot%5D", "html_url": "https://github.com/apps/github-actions", "followers_url": "https://api.github.com/users/github-actions%5Bbot%5D/followers", "following_url": "https://api.github.com/users/github-actions%5Bbot%5D/following{/other_user}", "gists_url": "https://api.github.com/users/github-actions%5Bbot%5D/gists{/gist_id}", "starred_url": "https://api.github.com/users/github-actions%5Bbot%5D/starred{/owner}{/repo}", "subscriptions_url": "https://api.github.com/users/github-actions%5Bbot%5D/subscriptions", "organizations_url": "https://api.github.com/users/github-actions%5Bbot%5D/orgs", "repos_url": "https://api.github.com/users/github-actions%5Bbot%5D/repos", "events_url": "https://api.github.com/users/github-actions%5Bbot%5D/events{/privacy}", "received_events_url": "https://api.github.com/users/github-actions%5Bbot%5D/received_events", "type": "Bot", "user_view_type": "public", "site_admin": false}, "node_id": "RE_kwDOAzqfmc4RVc2C", "tag_name": "v10.2.13", "target_commitish": "latest-release", "name": "v10.2.13", "draft": false, "immutable": false, "prerelease": false, "created_at": "2026-02-26T10:21:42Z", "updated_at": "2026-02-26T10:32:28Z", "published_at": "2026-02-26T10:32:28Z", "assets": [], "tarball_url": "https://api.github.com/repos/storybookjs/storybook/tarball/v10.2.13", "zipball_url": "https://api.github.com/repos/storybookjs/storybook/zipball/v10.2.13", "body": "## 10.2.13\n\n- Addon Pseudo-states: Process all nested css rules - [#33605](https://github.com/storybookjs/storybook/pull/33605), thanks @hpohlmeyer!\n- Builder-Vite: Prevent config duplication - [#33883](https://github.com/storybookjs/storybook/pull/33883), thanks @copilot-swe-agent!\n- CLI: Fix React native web A11y issues - [#33937](https://github.com/storybookjs/storybook/pull/33937), thanks @jonniebigodes!\n- Core: Avoid hanging when inferring args for recursive calls on DOM elemens - [#33922](https://github.com/storybookjs/storybook/pull/33922), thanks @valentinpalkovic!\n- Eslint: Fix ESLint 10 compatibility in eslint-plugin-storybook rules - [#33884](https://github.com/storybookjs/storybook/pull/33884), thanks @copilot-swe-agent!\n- Viewport: Prioritize story viewport globals and avoid user-global pollution - [#33849](https://github.com/storybookjs/storybook/pull/33849), thanks @ia319!\n", "mentions_count": 5}, {"url": "https://api.github.com/repos/storybookjs/storybook/releases/290388262", "assets_url": "https://api.github.com/repos/storybookjs/storybook/releases/290388262/assets", "upload_url": "https://uploads.github.com/repos/storybookjs/storybook/releases/290388262/assets{?name,label}", "html_url": "https://github.com/storybookjs/storybook/releases/tag/v10.3.0-alpha.11", "id": 290388262, "author": {"login": "github-actions[bot]", "id": 41898282, "node_id": "MDM6Qm90NDE4OTgyODI=", "avatar_url": "https://avatars.githubusercontent.com/in/15368?v=4", "gravatar_id": "", "url": "https://api.github.com/users/github-actions%5Bbot%5D", "html_url": "https://github.com/apps/github-actions", "followers_url": "https://api.github.com/users/github-actions%5Bbot%5D/followers", "following_url": "https://api.github.com/users/github-actions%5Bbot%5D/following{/other_user}", "gists_url": "https://api.github.com/users/github-actions%5Bbot%5D/gists{/gist_id}", "starred_url": "https://api.github.com/users/github-actions%5Bbot%5D/starred{/owner}{/repo}", "subscriptions_url": "https://api.github.com/users/github-actions%5Bbot%5D/subscriptions", "organizations_url": "https://api.github.com/users/github-actions%5Bbot%5D/orgs", "repos_url": "https://api.github.com/users/github-actions%5Bbot%5D/repos", "events_url": "https://api.github.com/users/github-actions%5Bbot%5D/events{/privacy}", "received_events_url": "https://api.github.com/users/github-actions%5Bbot%5D/received_events", "type": "Bot", "user_view_type": "public", "site_admin": false}, "node_id": "RE_kwDOAzqfmc4RTvkm", "tag_name": "v10.3.0-alpha.11", "target_commitish": "next-release", "name": "v10.3.0-alpha.11", "draft": false, "immutable": false, "prerelease": true, "created_at": "2026-02-25T14:24:20Z", "updated_at": "2026-02-25T14:33:21Z", "published_at": "2026-02-25T14:33:21Z", "assets": [], "tarball_url": "https://api.github.com/repos/storybookjs/storybook/tarball/v10.3.0-alpha.11", "zipball_url": "https://api.github.com/repos/storybookjs/storybook/zipball/v10.3.0-alpha.11", "body": "## 10.3.0-alpha.11\n\n- Addon Pseudo-states: Process all nested css rules - [#33605](https://github.com/storybookjs/storybook/pull/33605), thanks @hpohlmeyer!\n- Core: Avoid hanging when inferring args for recursive calls on DOM elemens - [#33922](https://github.com/storybookjs/storybook/pull/33922), thanks @valentinpalkovic!\n- Core: Sanitize inputs for save from controls - [#33868](https://github.com/storybookjs/storybook/pull/33868), thanks @valentinpalkovic!\n- Telemetry: Add project age - [#33910](https://github.com/storybookjs/storybook/pull/33910), thanks @shilman!\n- Viewport: Prioritize story viewport globals and avoid user-global pollution - [#33849](https://github.com/storybookjs/storybook/pull/33849), thanks @ia319!\n", "mentions_count": 4}, {"url": "https://api.github.com/repos/storybookjs/storybook/releases/289777488", "assets_url": "https://api.github.com/repos/storybookjs/storybook/releases/289777488/assets", "upload_url": "https://uploads.github.com/repos/storybookjs/storybook/releases/289777488/assets{?name,label}", "html_url": "https://github.com/storybookjs/storybook/releases/tag/v10.3.0-alpha.10", "id": 289777488, "author": {"login": "github-actions[bot]", "id": 41898282, "node_id": "MDM6Qm90NDE4OTgyODI=", "avatar_url": "https://avatars.githubusercontent.com/in/15368?v=4", "gravatar_id": "", "url": "https://api.github.com/users/github-actions%5Bbot%5D", "html_url": "https://github.com/apps/github-actions", "followers_url": "https://api.github.com/users/github-actions%5Bbot%5D/followers", "following_url": "https://api.github.com/users/github-actions%5Bbot%5D/following{/other_user}", "gists_url": "https://api.github.com/users/github-actions%5Bbot%5D/gists{/gist_id}", "starred_url": "https://api.github.com/users/github-actions%5Bbot%5D/starred{/owner}{/repo}", "subscriptions_url": "https://api.github.com/users/github-actions%5Bbot%5D/subscriptions", "organizations_url": "https://api.github.com/users/github-actions%5Bbot%5D/orgs", "repos_url": "https://api.github.com/users/github-actions%5Bbot%5D/repos", "events_url": "https://api.github.com/users/github-actions%5Bbot%5D/events{/privacy}", "received_events_url": "https://api.github.com/users/github-actions%5Bbot%5D/received_events", "type": "Bot", "user_view_type": "public", "site_admin": false}, "node_id": "RE_kwDOAzqfmc4RRadQ", "tag_name": "v10.3.0-alpha.10", "target_commitish": "next-release", "name": "v10.3.0-alpha.10", "draft": false, "immutable": false, "prerelease": true, "created_at": "2026-02-24T09:39:47Z", "updated_at": "2026-02-24T09:48:31Z", "published_at": "2026-02-24T09:48:31Z", "assets": [], "tarball_url": "https://api.github.com/repos/storybookjs/storybook/tarball/v10.3.0-alpha.10", "zipball_url": "https://api.github.com/repos/storybookjs/storybook/zipball/v10.3.0-alpha.10", "body": "## 10.3.0-alpha.10\n\n- Addon-Vitest: Fix postinstall a11y installation - [#33888](https://github.com/storybookjs/storybook/pull/33888), thanks @valentinpalkovic!\n- Builder-Vite: Use preview annotations as entry points for optimizeDeps - [#33875](https://github.com/storybookjs/storybook/pull/33875), thanks @copilot-swe-agent!\n- React Native Web: Fix inconsistent example stories - [#33891](https://github.com/storybookjs/storybook/pull/33891), thanks @danielalanbates!\n- Webpack: Improve performance of module-mocking plugins - [#33169](https://github.com/storybookjs/storybook/pull/33169), thanks @valentinpalkovic!\n", "reactions": {"url": "https://api.github.com/repos/storybookjs/storybook/releases/289777488/reactions", "total_count": 1, "+1": 1, "-1": 0, "laugh": 0, "hooray": 0, "confused": 0, "heart": 0, "rocket": 0, "eyes": 0}, "mentions_count": 3}, {"url": "https://api.github.com/repos/storybookjs/storybook/releases/289888397", "assets_url": "https://api.github.com/repos/storybookjs/storybook/releases/289888397/assets", "upload_url": "https://uploads.github.com/repos/storybookjs/storybook/releases/289888397/assets{?name,label}", "html_url": "https://github.com/storybookjs/storybook/releases/tag/v10.2.12", "id": 289888397, "author": {"login": "github-actions[bot]", "id": 41898282, "node_id": "MDM6Qm90NDE4OTgyODI=", "avatar_url": "https://avatars.githubusercontent.com/in/15368?v=4", "gravatar_id": "", "url": "https://api.github.com/users/github-actions%5Bbot%5D", "html_url": "https://github.com/apps/github-actions", "followers_url": "https://api.github.com/users/github-actions%5Bbot%5D/followers", "following_url": "https://api.github.com/users/github-actions%5Bbot%5D/following{/other_user}", "gists_url": "https://api.github.com/users/github-actions%5Bbot%5D/gists{/gist_id}", "starred_url": "https://api.github.com/users/github-actions%5Bbot%5D/starred{/owner}{/repo}", "subscriptions_url": "https://api.github.com/users/github-actions%5Bbot%5D/subscriptions", "organizations_url": "https://api.github.com/users/github-actions%5Bbot%5D/orgs", "repos_url": "https://api.github.com/users/github-actions%5Bbot%5D/repos", "events_url": "https://api.github.com/users/github-actions%5Bbot%5D/events{/privacy}", "received_events_url": "https://api.github.com/users/github-actions%5Bbot%5D/received_events", "type": "Bot", "user_view_type": "public", "site_admin": false}, "node_id": "RE_kwDOAzqfmc4RR1iN", "tag_name": "v10.2.12", "target_commitish": "latest-release", "name": "v10.2.12", "draft": false, "immutable": false, "prerelease": false, "created_at": "2026-02-24T14:20:27Z", "updated_at": "2026-02-24T14:31:06Z", "published_at": "2026-02-24T14:31:06Z", "assets": [], "tarball_url": "https://api.github.com/repos/storybookjs/storybook/tarball/v10.2.12", "zipball_url": "https://api.github.com/repos/storybookjs/storybook/zipball/v10.2.12", "body": "## 10.2.12\n\n- Core: Sanitize inputs for save from controls - [#33868](https://github.com/storybookjs/storybook/pull/33868), thanks @valentinpalkovic!\n- Telemetry: Add project age - [#33910](https://github.com/storybookjs/storybook/pull/33910), thanks @shilman!\n- Webpack: Improve performance of module-mocking plugins - [#33169](https://github.com/storybookjs/storybook/pull/33169), thanks @valentinpalkovic!\n", "mentions_count": 2}]}