{"d": {"total_count": 4358, "incomplete_results": false, "items": [{"id": 4813464, "node_id": "MDEwOlJlcG9zaXRvcnk0ODEzNDY0", "name": "supertest", "full_name": "forwardemail/supertest", "private": false, "owner": {"login": "forwardemail", "id": 32481436, "node_id": "MDEyOk9yZ2FuaXphdGlvbjMyNDgxNDM2", "avatar_url": "https://avatars.githubusercontent.com/u/32481436?v=4", "gravatar_id": "", "url": "https://api.github.com/users/forwardemail", "html_url": "https://github.com/forwardemail", "followers_url": "https://api.github.com/users/forwardemail/followers", "following_url": "https://api.github.com/users/forwardemail/following{/other_user}", "gists_url": "https://api.github.com/users/forwardemail/gists{/gist_id}", "starred_url": "https://api.github.com/users/forwardemail/starred{/owner}{/repo}", "subscriptions_url": "https://api.github.com/users/forwardemail/subscriptions", "organizations_url": "https://api.github.com/users/forwardemail/orgs", "repos_url": "https://api.github.com/users/forwardemail/repos", "events_url": "https://api.github.com/users/forwardemail/events{/privacy}", "received_events_url": "https://api.github.com/users/forwardemail/received_events", "type": "Organization", "user_view_type": "public", "site_admin": false}, "html_url": "https://github.com/forwardemail/supertest", "description": "\ud83d\udd77 Super-agent driven library for testing node.js HTTP servers using a fluent API.   Maintained for @forwardemail, @ladjs, @spamscanner, @breejs, @cabinjs, and @lassjs.", "fork": false, "url": "https://api.github.com/repos/forwardemail/supertest", "forks_url": "https://api.github.com/repos/forwardemail/supertest/forks", "keys_url": "https://api.github.com/repos/forwardemail/supertest/keys{/key_id}", "collaborators_url": "https://api.github.com/repos/forwardemail/supertest/collaborators{/collaborator}", "teams_url": "https://api.github.com/repos/forwardemail/supertest/teams", "hooks_url": "https://api.github.com/repos/forwardemail/supertest/hooks", "issue_events_url": "https://api.github.com/repos/forwardemail/supertest/issues/events{/number}", "events_url": "https://api.github.com/repos/forwardemail/supertest/events", "assignees_url": "https://api.github.com/repos/forwardemail/supertest/assignees{/user}", "branches_url": "https://api.github.com/repos/forwardemail/supertest/branches{/branch}", "tags_url": "https://api.github.com/repos/forwardemail/supertest/tags", "blobs_url": "https://api.github.com/repos/forwardemail/supertest/git/blobs{/sha}", "git_tags_url": "https://api.github.com/repos/forwardemail/supertest/git/tags{/sha}", "git_refs_url": "https://api.github.com/repos/forwardemail/supertest/git/refs{/sha}", "trees_url": "https://api.github.com/repos/forwardemail/supertest/git/trees{/sha}", "statuses_url": "https://api.github.com/repos/forwardemail/supertest/statuses/{sha}", "languages_url": "https://api.github.com/repos/forwardemail/supertest/languages", "stargazers_url": "https://api.github.com/repos/forwardemail/supertest/stargazers", "contributors_url": "https://api.github.com/repos/forwardemail/supertest/contributors", "subscribers_url": "https://api.github.com/repos/forwardemail/supertest/subscribers", "subscription_url": "https://api.github.com/repos/forwardemail/supertest/subscription", "commits_url": "https://api.github.com/repos/forwardemail/supertest/commits{/sha}", "git_commits_url": "https://api.github.com/repos/forwardemail/supertest/git/commits{/sha}", "comments_url": "https://api.github.com/repos/forwardemail/supertest/comments{/number}", "issue_comment_url": "https://api.github.com/repos/forwardemail/supertest/issues/comments{/number}", "contents_url": "https://api.github.com/repos/forwardemail/supertest/contents/{+path}", "compare_url": "https://api.github.com/repos/forwardemail/supertest/compare/{base}...{head}", "merges_url": "https://api.github.com/repos/forwardemail/supertest/merges", "archive_url": "https://api.github.com/repos/forwardemail/supertest/{archive_format}{/ref}", "downloads_url": "https://api.github.com/repos/forwardemail/supertest/downloads", "issues_url": "https://api.github.com/repos/forwardemail/supertest/issues{/number}", "pulls_url": "https://api.github.com/repos/forwardemail/supertest/pulls{/number}", "milestones_url": "https://api.github.com/repos/forwardemail/supertest/milestones{/number}", "notifications_url": "https://api.github.com/repos/forwardemail/supertest/notifications{?since,all,participating}", "labels_url": "https://api.github.com/repos/forwardemail/supertest/labels{/name}", "releases_url": "https://api.github.com/repos/forwardemail/supertest/releases{/id}", "deployments_url": "https://api.github.com/repos/forwardemail/supertest/deployments", "created_at": "2012-06-27T20:56:12Z", "updated_at": "2026-02-27T20:44:48Z", "pushed_at": "2026-02-14T12:43:11Z", "git_url": "git://github.com/forwardemail/supertest.git", "ssh_url": "git@github.com:forwardemail/supertest.git", "clone_url": "https://github.com/forwardemail/supertest.git", "svn_url": "https://github.com/forwardemail/supertest", "homepage": "", "size": 873, "stargazers_count": 14324, "watchers_count": 14324, "language": "JavaScript", "has_issues": true, "has_projects": true, "has_downloads": true, "has_wiki": false, "has_pages": false, "has_discussions": false, "forks_count": 782, "mirror_url": null, "archived": false, "disabled": false, "open_issues_count": 180, "license": {"key": "mit", "name": "MIT License", "spdx_id": "MIT", "url": "https://api.github.com/licenses/mit", "node_id": "MDc6TGljZW5zZTEz"}, "allow_forking": true, "is_template": false, "web_commit_signoff_required": false, "has_pull_requests": true, "pull_request_creation_policy": "all", "topics": ["assertions", "node", "superagent", "supertest"], "visibility": "public", "forks": 782, "open_issues": 180, "watchers": 14324, "default_branch": "master", "permissions": {"admin": false, "maintain": false, "push": false, "triage": false, "pull": true}, "score": 1.0}, {"id": 397731209, "node_id": "MDEwOlJlcG9zaXRvcnkzOTc3MzEyMDk=", "name": "express-typescript-skeleton", "full_name": "borjapazr/express-typescript-skeleton", "private": false, "owner": {"login": "borjapazr", "id": 9295713, "node_id": "MDQ6VXNlcjkyOTU3MTM=", "avatar_url": "https://avatars.githubusercontent.com/u/9295713?v=4", "gravatar_id": "", "url": "https://api.github.com/users/borjapazr", "html_url": "https://github.com/borjapazr", "followers_url": "https://api.github.com/users/borjapazr/followers", "following_url": "https://api.github.com/users/borjapazr/following{/other_user}", "gists_url": "https://api.github.com/users/borjapazr/gists{/gist_id}", "starred_url": "https://api.github.com/users/borjapazr/starred{/owner}{/repo}", "subscriptions_url": "https://api.github.com/users/borjapazr/subscriptions", "organizations_url": "https://api.github.com/users/borjapazr/orgs", "repos_url": "https://api.github.com/users/borjapazr/repos", "events_url": "https://api.github.com/users/borjapazr/events{/privacy}", "received_events_url": "https://api.github.com/users/borjapazr/received_events", "type": "User", "user_view_type": "public", "site_admin": false}, "html_url": "https://github.com/borjapazr/express-typescript-skeleton", "description": "\ud83d\udd30\ud83e\uddb8 Template to start developing a REST API with Node.js (Express), TypeScript, Ts.ED, ESLint, Prettier, Husky, Prisma, etc.", "fork": false, "url": "https://api.github.com/repos/borjapazr/express-typescript-skeleton", "forks_url": "https://api.github.com/repos/borjapazr/express-typescript-skeleton/forks", "keys_url": "https://api.github.com/repos/borjapazr/express-typescript-skeleton/keys{/key_id}", "collaborators_url": "https://api.github.com/repos/borjapazr/express-typescript-skeleton/collaborators{/collaborator}", "teams_url": "https://api.github.com/repos/borjapazr/express-typescript-skeleton/teams", "hooks_url": "https://api.github.com/repos/borjapazr/express-typescript-skeleton/hooks", "issue_events_url": "https://api.github.com/repos/borjapazr/express-typescript-skeleton/issues/events{/number}", "events_url": "https://api.github.com/repos/borjapazr/express-typescript-skeleton/events", "assignees_url": "https://api.github.com/repos/borjapazr/express-typescript-skeleton/assignees{/user}", "branches_url": "https://api.github.com/repos/borjapazr/express-typescript-skeleton/branches{/branch}", "tags_url": "https://api.github.com/repos/borjapazr/express-typescript-skeleton/tags", "blobs_url": "https://api.github.com/repos/borjapazr/express-typescript-skeleton/git/blobs{/sha}", "git_tags_url": "https://api.github.com/repos/borjapazr/express-typescript-skeleton/git/tags{/sha}", "git_refs_url": "https://api.github.com/repos/borjapazr/express-typescript-skeleton/git/refs{/sha}", "trees_url": "https://api.github.com/repos/borjapazr/express-typescript-skeleton/git/trees{/sha}", "statuses_url": "https://api.github.com/repos/borjapazr/express-typescript-skeleton/statuses/{sha}", "languages_url": "https://api.github.com/repos/borjapazr/express-typescript-skeleton/languages", "stargazers_url": "https://api.github.com/repos/borjapazr/express-typescript-skeleton/stargazers", "contributors_url": "https://api.github.com/repos/borjapazr/express-typescript-skeleton/contributors", "subscribers_url": "https://api.github.com/repos/borjapazr/express-typescript-skeleton/subscribers", "subscription_url": "https://api.github.com/repos/borjapazr/express-typescript-skeleton/subscription", "commits_url": "https://api.github.com/repos/borjapazr/express-typescript-skeleton/commits{/sha}", "git_commits_url": "https://api.github.com/repos/borjapazr/express-typescript-skeleton/git/commits{/sha}", "comments_url": "https://api.github.com/repos/borjapazr/express-typescript-skeleton/comments{/number}", "issue_comment_url": "https://api.github.com/repos/borjapazr/express-typescript-skeleton/issues/comments{/number}", "contents_url": "https://api.github.com/repos/borjapazr/express-typescript-skeleton/contents/{+path}", "compare_url": "https://api.github.com/repos/borjapazr/express-typescript-skeleton/compare/{base}...{head}", "merges_url": "https://api.github.com/repos/borjapazr/express-typescript-skeleton/merges", "archive_url": "https://api.github.com/repos/borjapazr/express-typescript-skeleton/{archive_format}{/ref}", "downloads_url": "https://api.github.com/repos/borjapazr/express-typescript-skeleton/downloads", "issues_url": "https://api.github.com/repos/borjapazr/express-typescript-skeleton/issues{/number}", "pulls_url": "https://api.github.com/repos/borjapazr/express-typescript-skeleton/pulls{/number}", "milestones_url": "https://api.github.com/repos/borjapazr/express-typescript-skeleton/milestones{/number}", "notifications_url": "https://api.github.com/repos/borjapazr/express-typescript-skeleton/notifications{?since,all,participating}", "labels_url": "https://api.github.com/repos/borjapazr/express-typescript-skeleton/labels{/name}", "releases_url": "https://api.github.com/repos/borjapazr/express-typescript-skeleton/releases{/id}", "deployments_url": "https://api.github.com/repos/borjapazr/express-typescript-skeleton/deployments", "created_at": "2021-08-18T20:48:02Z", "updated_at": "2026-02-21T21:46:41Z", "pushed_at": "2025-11-25T11:08:06Z", "git_url": "git://github.com/borjapazr/express-typescript-skeleton.git", "ssh_url": "git@github.com:borjapazr/express-typescript-skeleton.git", "clone_url": "https://github.com/borjapazr/express-typescript-skeleton.git", "svn_url": "https://github.com/borjapazr/express-typescript-skeleton", "homepage": "https://express-typescript-skeleton.bpaz.dev/api/docs", "size": 6891, "stargazers_count": 586, "watchers_count": 586, "language": "TypeScript", "has_issues": true, "has_projects": true, "has_downloads": true, "has_wiki": true, "has_pages": false, "has_discussions": false, "forks_count": 71, "mirror_url": null, "archived": true, "disabled": false, "open_issues_count": 14, "license": {"key": "mit", "name": "MIT License", "spdx_id": "MIT", "url": "https://api.github.com/licenses/mit", "node_id": "MDc6TGljZW5zZTEz"}, "allow_forking": true, "is_template": true, "web_commit_signoff_required": false, "has_pull_requests": true, "pull_request_creation_policy": "all", "topics": ["best-practices", "ddd", "docker", "docker-compose", "dockerfile", "eslint", "express", "hacktoberfest", "hexagonal-architecture", "jest", "jwt", "makefile", "nodejs", "pm2", "prettier", "prisma", "supertest", "tsconfig-paths", "tsed", "typescript"], "visibility": "public", "forks": 71, "open_issues": 14, "watchers": 586, "default_branch": "main", "permissions": {"admin": false, "maintain": false, "push": false, "triage": false, "pull": true}, "score": 1.0}, {"id": 171186954, "node_id": "MDEwOlJlcG9zaXRvcnkxNzExODY5NTQ=", "name": "nest-user-auth", "full_name": "EricKit/nest-user-auth", "private": false, "owner": {"login": "EricKit", "id": 4143477, "node_id": "MDQ6VXNlcjQxNDM0Nzc=", "avatar_url": "https://avatars.githubusercontent.com/u/4143477?v=4", "gravatar_id": "", "url": "https://api.github.com/users/EricKit", "html_url": "https://github.com/EricKit", "followers_url": "https://api.github.com/users/EricKit/followers", "following_url": "https://api.github.com/users/EricKit/following{/other_user}", "gists_url": "https://api.github.com/users/EricKit/gists{/gist_id}", "starred_url": "https://api.github.com/users/EricKit/starred{/owner}{/repo}", "subscriptions_url": "https://api.github.com/users/EricKit/subscriptions", "organizations_url": "https://api.github.com/users/EricKit/orgs", "repos_url": "https://api.github.com/users/EricKit/repos", "events_url": "https://api.github.com/users/EricKit/events{/privacy}", "received_events_url": "https://api.github.com/users/EricKit/received_events", "type": "User", "user_view_type": "public", "site_admin": false}, "html_url": "https://github.com/EricKit/nest-user-auth", "description": "A starter build for a back end which implements managing users with MongoDB, Mongoose, NestJS, Passport-JWT, and GraphQL.", "fork": false, "url": "https://api.github.com/repos/EricKit/nest-user-auth", "forks_url": "https://api.github.com/repos/EricKit/nest-user-auth/forks", "keys_url": "https://api.github.com/repos/EricKit/nest-user-auth/keys{/key_id}", "collaborators_url": "https://api.github.com/repos/EricKit/nest-user-auth/collaborators{/collaborator}", "teams_url": "https://api.github.com/repos/EricKit/nest-user-auth/teams", "hooks_url": "https://api.github.com/repos/EricKit/nest-user-auth/hooks", "issue_events_url": "https://api.github.com/repos/EricKit/nest-user-auth/issues/events{/number}", "events_url": "https://api.github.com/repos/EricKit/nest-user-auth/events", "assignees_url": "https://api.github.com/repos/EricKit/nest-user-auth/assignees{/user}", "branches_url": "https://api.github.com/repos/EricKit/nest-user-auth/branches{/branch}", "tags_url": "https://api.github.com/repos/EricKit/nest-user-auth/tags", "blobs_url": "https://api.github.com/repos/EricKit/nest-user-auth/git/blobs{/sha}", "git_tags_url": "https://api.github.com/repos/EricKit/nest-user-auth/git/tags{/sha}", "git_refs_url": "https://api.github.com/repos/EricKit/nest-user-auth/git/refs{/sha}", "trees_url": "https://api.github.com/repos/EricKit/nest-user-auth/git/trees{/sha}", "statuses_url": "https://api.github.com/repos/EricKit/nest-user-auth/statuses/{sha}", "languages_url": "https://api.github.com/repos/EricKit/nest-user-auth/languages", "stargazers_url": "https://api.github.com/repos/EricKit/nest-user-auth/stargazers", "contributors_url": "https://api.github.com/repos/EricKit/nest-user-auth/contributors", "subscribers_url": "https://api.github.com/repos/EricKit/nest-user-auth/subscribers", "subscription_url": "https://api.github.com/repos/EricKit/nest-user-auth/subscription", "commits_url": "https://api.github.com/repos/EricKit/nest-user-auth/commits{/sha}", "git_commits_url": "https://api.github.com/repos/EricKit/nest-user-auth/git/commits{/sha}", "comments_url": "https://api.github.com/repos/EricKit/nest-user-auth/comments{/number}", "issue_comment_url": "https://api.github.com/repos/EricKit/nest-user-auth/issues/comments{/number}", "contents_url": "https://api.github.com/repos/EricKit/nest-user-auth/contents/{+path}", "compare_url": "https://api.github.com/repos/EricKit/nest-user-auth/compare/{base}...{head}", "merges_url": "https://api.github.com/repos/EricKit/nest-user-auth/merges", "archive_url": "https://api.github.com/repos/EricKit/nest-user-auth/{archive_format}{/ref}", "downloads_url": "https://api.github.com/repos/EricKit/nest-user-auth/downloads", "issues_url": "https://api.github.com/repos/EricKit/nest-user-auth/issues{/number}", "pulls_url": "https://api.github.com/repos/EricKit/nest-user-auth/pulls{/number}", "milestones_url": "https://api.github.com/repos/EricKit/nest-user-auth/milestones{/number}", "notifications_url": "https://api.github.com/repos/EricKit/nest-user-auth/notifications{?since,all,participating}", "labels_url": "https://api.github.com/repos/EricKit/nest-user-auth/labels{/name}", "releases_url": "https://api.github.com/repos/EricKit/nest-user-auth/releases{/id}", "deployments_url": "https://api.github.com/repos/EricKit/nest-user-auth/deployments", "created_at": "2019-02-18T00:02:58Z", "updated_at": "2025-10-31T14:26:50Z", "pushed_at": "2023-04-11T19:16:14Z", "git_url": "git://github.com/EricKit/nest-user-auth.git", "ssh_url": "git@github.com:EricKit/nest-user-auth.git", "clone_url": "https://github.com/EricKit/nest-user-auth.git", "svn_url": "https://github.com/EricKit/nest-user-auth", "homepage": "", "size": 803, "stargazers_count": 295, "watchers_count": 295, "language": "TypeScript", "has_issues": true, "has_projects": true, "has_downloads": true, "has_wiki": true, "has_pages": false, "has_discussions": true, "forks_count": 39, "mirror_url": null, "archived": false, "disabled": false, "open_issues_count": 17, "license": {"key": "mit", "name": "MIT License", "spdx_id": "MIT", "url": "https://api.github.com/licenses/mit", "node_id": "MDc6TGljZW5zZTEz"}, "allow_forking": true, "is_template": false, "web_commit_signoff_required": false, "has_pull_requests": true, "pull_request_creation_policy": "all", "topics": ["apollo-server", "authentication", "backend", "graphql", "jest", "joi", "mongo", "mongodb", "mongoose", "nest", "nestjs", "node", "nodejs", "nodemailer", "passport-jwt", "passportjs", "supertest", "user-management"], "visibility": "public", "forks": 39, "open_issues": 17, "watchers": 295, "default_branch": "master", "permissions": {"admin": false, "maintain": false, "push": false, "triage": false, "pull": true}, "score": 1.0}]}}